bfio/VERSION
bfio/__init__.py
bfio/backends.py
bfio/base_classes.py
bfio/bfio.py
bfio/ts_backends.py
bfio/utils.py
bfio-2.4.8.dist-info/licenses/LICENSE
bfio-2.4.8.dist-info/METADATA
bfio-2.4.8.dist-info/WHEEL
bfio-2.4.8.dist-info/top_level.txt
bfio-2.4.8.dist-info/RECORD
