Metadata-Version: 2.4
Name: bfio
Version: 2.4.8
Summary: Simple reading and writing classes for tiled tiffs using Bio-Formats.
Author-email: Nick Schaub <nick.schaub@nih.gov>, Sameeul Bashir Samee <sameeul.samee@axleinfo.com>
Maintainer-email: Sameeul Bashir Samee <sameeul.samee@axleinfo.com>
License: MIT License
Project-URL: Documentation, https://bfio.readthedocs.io/en/latest/
Project-URL: Repository, https://github.com/PolusAI/bfio
Classifier: Development Status :: 5 - Production/Stable
Classifier: Programming Language :: Python :: 3
Classifier: License :: OSI Approved :: MIT License
Classifier: Operating System :: OS Independent
Requires-Python: >=3.8
License-File: LICENSE
Requires-Dist: imagecodecs>=2021.2.26
Requires-Dist: numpy
Requires-Dist: ome-types>=0.4.2
Requires-Dist: zarr<3,>=2.6.1
Requires-Dist: scyjava
Requires-Dist: jpype1
Requires-Dist: tifffile>=2022.8.12
Requires-Dist: bfiocpp
Provides-Extra: dev
Requires-Dist: ome_zarr; extra == "dev"
Requires-Dist: pillow; extra == "dev"
Requires-Dist: requests>=2.26.0; extra == "dev"
Dynamic: license-file
